nekoyume/__init__.py
nekoyume/api.py
nekoyume/app.py
nekoyume/block.py
nekoyume/broadcast.py
nekoyume/cli.py
nekoyume/exc.py
nekoyume/game.py
nekoyume/hashcash.py
nekoyume/move.py
nekoyume/node.py
nekoyume/orm.py
nekoyume/shell.py
nekoyume/tasks.py
nekoyume/user.py
nekoyume/util.py
nekoyume/battle/__init__.py
nekoyume/battle/__main__.py
nekoyume/battle/characters.py
nekoyume/battle/enums.py
nekoyume/battle/logger.py
nekoyume/battle/simul.py
nekoyume/battle/utils.py
nekoyume/battle/components/__init__.py
nekoyume/battle/components/bag.py
nekoyume/battle/components/buff.py
nekoyume/battle/components/stats.py
nekoyume/battle/components/behaviors/__init__.py
nekoyume/battle/components/behaviors/aggro.py
nekoyume/battle/components/behaviors/skills/__init__.py
nekoyume/battle/status/__init__.py
nekoyume/battle/status/base.py
nekoyume/battle/status/item.py
nekoyume/battle/status/skills.py
nekoyume/battle/status/spawn.py
nekoyume/battle/status/stats.py
nekoyume/battle/status/zone.py
nekoyume/items/__init__.py
nekoyume/items/armors.py
nekoyume/items/base.py
nekoyume/items/foods.py
nekoyume/items/heads.py
nekoyume/items/weapons.py
nekoyume/tables/__init__.py
nekoyume/translations/ja/LC_MESSAGES/messages.po
nekoyume/translations/ko/LC_MESSAGES/messages.po
nekoyume-0.1.4.dist-info/DESCRIPTION.rst
nekoyume-0.1.4.dist-info/METADATA
nekoyume-0.1.4.dist-info/RECORD
nekoyume-0.1.4.dist-info/WHEEL
nekoyume-0.1.4.dist-info/entry_points.txt
nekoyume-0.1.4.dist-info/metadata.json
nekoyume-0.1.4.dist-info/top_level.txt
