Metadata-Version: 2.0
Name: nekoyume
Version: 0.1.4
Summary: Decentralized MMORPG based on Dungeon World
Home-page: https://github.com/nekoyume/nekoyume
Author: JC Kim
Author-email: jc@nekoyu.me
License: LICENSE.txt
Project-URL: Bug Reports, https://github.com/nekoyume/nekoyume/issues
Project-URL: Funding, https://nekoyu.me/
Project-URL: Source, https://github.com/nekoyume/nekoyume/
Keywords: blockchain mmorpg game
Platform: UNKNOWN
Classifier: Development Status :: 2 - Pre-Alpha
Classifier: Intended Audience :: Other Audience
Classifier: Topic :: Database :: Database Engines/Servers
Classifier: Topic :: Games/Entertainment :: Role-Playing
Classifier: License :: OSI Approved :: MIT License
Classifier: Programming Language :: Python :: 3.6
Provides-Extra: dev
Provides-Extra: test
Requires-Dist: bencode.py (<2.1.0,>=2.0.0)
Requires-Dist: blinker (<1.5,>=1.4)
Requires-Dist: celery (<4.2.0,>=4.1.0)
Requires-Dist: click (<7.0,>=6.7)
Requires-Dist: cykeccak (<0.14.0.0,>=0.13.2.2)
Requires-Dist: dataclasses (<1.0,>=0.6)
Requires-Dist: Flask (<0.13.0,>=0.12.2)
Requires-Dist: Flask-Babel (<0.12.0,>=0.11.2)
Requires-Dist: Flask-Caching (<1.5.0,>=1.4.0)
Requires-Dist: Flask-SQLAlchemy (<2.4.0,>=2.3.2)
Requires-Dist: gevent (==1.3.5)
Requires-Dist: gunicorn (>=19.9.0)
Requires-Dist: psycopg2 (<2.8.0,>=2.7.5)
Requires-Dist: ptpython (==0.41)
Requires-Dist: pytz (>=2018.3)
Requires-Dist: sentry-sdk[flask] (==0.4.1)
Requires-Dist: redis (<2.11.0,>=2.10.6)
Requires-Dist: requests (<2.20.0,>=2.19.1)
Requires-Dist: coincurve (>=9.0.0)
Requires-Dist: SQLAlchemy (<1.3.0,>=1.2.2)
Requires-Dist: tablib (<0.13.0,>=0.12.1)
Requires-Dist: typeguard (<2.3.0,>=2.2.2)
Requires-Dist: urllib3 (==1.23)
Provides-Extra: dev
Requires-Dist: flake8 (<3.6.0,>=3.5.0); extra == 'dev'
Requires-Dist: flake8-import-order-spoqa (<1.6.0,>=1.5.0); extra == 'dev'
Requires-Dist: recommonmark (==0.4.0); extra == 'dev'
Requires-Dist: Sphinx (<1.8.0,>=1.7.1); extra == 'dev'
Requires-Dist: sphinx-rtd-theme (==0.2.4); extra == 'dev'
Provides-Extra: test
Requires-Dist: codecov (<2.1.0,>=2.0.15); extra == 'test'
Requires-Dist: pytest (<3.9.0,>=3.8.0); extra == 'test'
Requires-Dist: pytest-flake8 (<1.1.0,>=1.0.2); extra == 'test'
Requires-Dist: pytest-localserver (<0.5,>=0.4.1); extra == 'test'
Requires-Dist: requests-mock (<1.6.0,>=1.5.2); extra == 'test'
